{"nodes": [{"id": "src_renderer_src_features_character_model_derive_character_stage_sections_ts", "label": "derive-character-stage-sections.ts", "file_type": "code", "source_file": "src\\renderer\\src\\features\\character\\model\\derive-character-stage-sections.ts", "source_location": "L1"}, {"id": "derive_character_stage_sections_normalizename", "label": "normalizeName()", "file_type": "code", "source_file": "src\\renderer\\src\\features\\character\\model\\derive-character-stage-sections.ts", "source_location": "L32"}, {"id": "derive_character_stage_sections_getrolelayerlabel", "label": "getRoleLayerLabel()", "file_type": "code", "source_file": "src\\renderer\\src\\features\\character\\model\\derive-character-stage-sections.ts", "source_location": "L88"}, {"id": "derive_character_stage_sections_getfactiontypelabel", "label": "getFactionTypeLabel()", "file_type": "code", "source_file": "src\\renderer\\src\\features\\character\\model\\derive-character-stage-sections.ts", "source_location": "L99"}, {"id": "derive_character_stage_sections_byrolethenname", "label": "byRoleThenName()", "file_type": "code", "source_file": "src\\renderer\\src\\features\\character\\model\\derive-character-stage-sections.ts", "source_location": "L114"}, {"id": "derive_character_stage_sections_normalizepreviewvalue", "label": "normalizePreviewValue()", "file_type": "code", "source_file": "src\\renderer\\src\\features\\character\\model\\derive-character-stage-sections.ts", "source_location": "L120"}, {"id": "derive_character_stage_sections_joinpreviewvalues", "label": "joinPreviewValues()", "file_type": "code", "source_file": "src\\renderer\\src\\features\\character\\model\\derive-character-stage-sections.ts", "source_location": "L127"}, {"id": "derive_character_stage_sections_buildfactionplaceholderseats", "label": "buildFactionPlaceholderSeats()", "file_type": "code", "source_file": "src\\renderer\\src\\features\\character\\model\\derive-character-stage-sections.ts", "source_location": "L141"}, {"id": "derive_character_stage_sections_buildfactionslotseats", "label": "buildFactionSlotSeats()", "file_type": "code", "source_file": "src\\renderer\\src\\features\\character\\model\\derive-character-stage-sections.ts", "source_location": "L172"}, {"id": "derive_character_stage_sections_resolvefullprofileentityids", "label": "resolveFullProfileEntityIds()", "file_type": "code", "source_file": "src\\renderer\\src\\features\\character\\model\\derive-character-stage-sections.ts", "source_location": "L191"}, {"id": "derive_character_stage_sections_buildlightcards", "label": "buildLightCards()", "file_type": "code", "source_file": "src\\renderer\\src\\features\\character\\model\\derive-character-stage-sections.ts", "source_location": "L222"}, {"id": "derive_character_stage_sections_buildfactionroster", "label": "buildFactionRoster()", "file_type": "code", "source_file": "src\\renderer\\src\\features\\character\\model\\derive-character-stage-sections.ts", "source_location": "L259"}, {"id": "derive_character_stage_sections_buildcharacterstagesections", "label": "buildCharacterStageSections()", "file_type": "code", "source_file": "src\\renderer\\src\\features\\character\\model\\derive-character-stage-sections.ts", "source_location": "L307"}, {"id": "derive_character_stage_sections_createcharacterdraftfromentitystore", "label": "createCharacterDraftFromEntityStore()", "file_type": "code", "source_file": "src\\renderer\\src\\features\\character\\model\\derive-character-stage-sections.ts", "source_location": "L325"}], "edges": [{"source": "src_renderer_src_features_character_model_derive_character_stage_sections_ts", "target": "src_shared_contracts_entities_ts", "relation": "imports_from", "confidence": "EXTRACTED", "source_file": "src\\renderer\\src\\features\\character\\model\\derive-character-stage-sections.ts", "source_location": "L1", "weight": 1.0}, {"source": "src_renderer_src_features_character_model_derive_character_stage_sections_ts", "target": "src_shared_contracts_workflow_ts", "relation": "imports_from", "confidence": "EXTRACTED", "source_file": "src\\renderer\\src\\features\\character\\model\\derive-character-stage-sections.ts", "source_location": "L6", "weight": 1.0}, {"source": "src_renderer_src_features_character_model_derive_character_stage_sections_ts", "target": "src_shared_domain_entities_character_draft_mapper_ts", "relation": "imports_from", "confidence": "EXTRACTED", "source_file": "src\\renderer\\src\\features\\character\\model\\derive-character-stage-sections.ts", "source_location": "L7", "weight": 1.0}, {"source": "src_renderer_src_features_character_model_derive_character_stage_sections_ts", "target": "src_shared_domain_entities_faction_seat_characters_ts", "relation": "imports_from", "confidence": "EXTRACTED", "source_file": "src\\renderer\\src\\features\\character\\model\\derive-character-stage-sections.ts", "source_location": "L12", "weight": 1.0}, {"source": "src_renderer_src_features_character_model_derive_character_stage_sections_ts", "target": "derive_character_stage_sections_normalizename", "relation": "contains", "confidence": "EXTRACTED", "source_file": "src\\renderer\\src\\features\\character\\model\\derive-character-stage-sections.ts", "source_location": "L32", "weight": 1.0}, {"source": "src_renderer_src_features_character_model_derive_character_stage_sections_ts", "target": "derive_character_stage_sections_getrolelayerlabel", "relation": "contains", "confidence": "EXTRACTED", "source_file": "src\\renderer\\src\\features\\character\\model\\derive-character-stage-sections.ts", "source_location": "L88", "weight": 1.0}, {"source": "src_renderer_src_features_character_model_derive_character_stage_sections_ts", "target": "derive_character_stage_sections_getfactiontypelabel", "relation": "contains", "confidence": "EXTRACTED", "source_file": "src\\renderer\\src\\features\\character\\model\\derive-character-stage-sections.ts", "source_location": "L99", "weight": 1.0}, {"source": "src_renderer_src_features_character_model_derive_character_stage_sections_ts", "target": "derive_character_stage_sections_byrolethenname", "relation": "contains", "confidence": "EXTRACTED", "source_file": "src\\renderer\\src\\features\\character\\model\\derive-character-stage-sections.ts", "source_location": "L114", "weight": 1.0}, {"source": "src_renderer_src_features_character_model_derive_character_stage_sections_ts", "target": "derive_character_stage_sections_normalizepreviewvalue", "relation": "contains", "confidence": "EXTRACTED", "source_file": "src\\renderer\\src\\features\\character\\model\\derive-character-stage-sections.ts", "source_location": "L120", "weight": 1.0}, {"source": "src_renderer_src_features_character_model_derive_character_stage_sections_ts", "target": "derive_character_stage_sections_joinpreviewvalues", "relation": "contains", "confidence": "EXTRACTED", "source_file": "src\\renderer\\src\\features\\character\\model\\derive-character-stage-sections.ts", "source_location": "L127", "weight": 1.0}, {"source": "src_renderer_src_features_character_model_derive_character_stage_sections_ts", "target": "derive_character_stage_sections_buildfactionplaceholderseats", "relation": "contains", "confidence": "EXTRACTED", "source_file": "src\\renderer\\src\\features\\character\\model\\derive-character-stage-sections.ts", "source_location": "L141", "weight": 1.0}, {"source": "src_renderer_src_features_character_model_derive_character_stage_sections_ts", "target": "derive_character_stage_sections_buildfactionslotseats", "relation": "contains", "confidence": "EXTRACTED", "source_file": "src\\renderer\\src\\features\\character\\model\\derive-character-stage-sections.ts", "source_location": "L172", "weight": 1.0}, {"source": "src_renderer_src_features_character_model_derive_character_stage_sections_ts", "target": "derive_character_stage_sections_resolvefullprofileentityids", "relation": "contains", "confidence": "EXTRACTED", "source_file": "src\\renderer\\src\\features\\character\\model\\derive-character-stage-sections.ts", "source_location": "L191", "weight": 1.0}, {"source": "src_renderer_src_features_character_model_derive_character_stage_sections_ts", "target": "derive_character_stage_sections_buildlightcards", "relation": "contains", "confidence": "EXTRACTED", "source_file": "src\\renderer\\src\\features\\character\\model\\derive-character-stage-sections.ts", "source_location": "L222", "weight": 1.0}, {"source": "src_renderer_src_features_character_model_derive_character_stage_sections_ts", "target": "derive_character_stage_sections_buildfactionroster", "relation": "contains", "confidence": "EXTRACTED", "source_file": "src\\renderer\\src\\features\\character\\model\\derive-character-stage-sections.ts", "source_location": "L259", "weight": 1.0}, {"source": "src_renderer_src_features_character_model_derive_character_stage_sections_ts", "target": "derive_character_stage_sections_buildcharacterstagesections", "relation": "contains", "confidence": "EXTRACTED", "source_file": "src\\renderer\\src\\features\\character\\model\\derive-character-stage-sections.ts", "source_location": "L307", "weight": 1.0}, {"source": "src_renderer_src_features_character_model_derive_character_stage_sections_ts", "target": "derive_character_stage_sections_createcharacterdraftfromentitystore", "relation": "contains", "confidence": "EXTRACTED", "source_file": "src\\renderer\\src\\features\\character\\model\\derive-character-stage-sections.ts", "source_location": "L325", "weight": 1.0}, {"source": "derive_character_stage_sections_joinpreviewvalues", "target": "derive_character_stage_sections_normalizepreviewvalue", "relation": "calls", "confidence": "EXTRACTED", "source_file": "src\\renderer\\src\\features\\character\\model\\derive-character-stage-sections.ts", "source_location": "L132", "weight": 1.0}, {"source": "derive_character_stage_sections_resolvefullprofileentityids", "target": "derive_character_stage_sections_normalizename", "relation": "calls", "confidence": "EXTRACTED", "source_file": "src\\renderer\\src\\features\\character\\model\\derive-character-stage-sections.ts", "source_location": "L198", "weight": 1.0}, {"source": "derive_character_stage_sections_buildcharacterstagesections", "target": "derive_character_stage_sections_resolvefullprofileentityids", "relation": "calls", "confidence": "EXTRACTED", "source_file": "src\\renderer\\src\\features\\character\\model\\derive-character-stage-sections.ts", "source_location": "L313", "weight": 1.0}, {"source": "derive_character_stage_sections_buildcharacterstagesections", "target": "derive_character_stage_sections_buildfactionroster", "relation": "calls", "confidence": "EXTRACTED", "source_file": "src\\renderer\\src\\features\\character\\model\\derive-character-stage-sections.ts", "source_location": "L314", "weight": 1.0}, {"source": "derive_character_stage_sections_buildcharacterstagesections", "target": "derive_character_stage_sections_buildlightcards", "relation": "calls", "confidence": "EXTRACTED", "source_file": "src\\renderer\\src\\features\\character\\model\\derive-character-stage-sections.ts", "source_location": "L319", "weight": 1.0}], "raw_calls": [{"caller_nid": "derive_character_stage_sections_normalizename", "callee": "toLowerCase", "source_file": "src\\renderer\\src\\features\\character\\model\\derive-character-stage-sections.ts", "source_location": "L33"}, {"caller_nid": "derive_character_stage_sections_normalizename", "callee": "trim", "source_file": "src\\renderer\\src\\features\\character\\model\\derive-character-stage-sections.ts", "source_location": "L33"}, {"caller_nid": "derive_character_stage_sections_byrolethenname", "callee": "localeCompare", "source_file": "src\\renderer\\src\\features\\character\\model\\derive-character-stage-sections.ts", "source_location": "L117"}, {"caller_nid": "derive_character_stage_sections_normalizepreviewvalue", "callee": "trim", "source_file": "src\\renderer\\src\\features\\character\\model\\derive-character-stage-sections.ts", "source_location": "L121"}, {"caller_nid": "derive_character_stage_sections_normalizepreviewvalue", "callee": "replace", "source_file": "src\\renderer\\src\\features\\character\\model\\derive-character-stage-sections.ts", "source_location": "L121"}, {"caller_nid": "derive_character_stage_sections_normalizepreviewvalue", "callee": "replace", "source_file": "src\\renderer\\src\\features\\character\\model\\derive-character-stage-sections.ts", "source_location": "L121"}, {"caller_nid": "derive_character_stage_sections_joinpreviewvalues", "callee": "has", "source_file": "src\\renderer\\src\\features\\character\\model\\derive-character-stage-sections.ts", "source_location": "L133"}, {"caller_nid": "derive_character_stage_sections_joinpreviewvalues", "callee": "add", "source_file": "src\\renderer\\src\\features\\character\\model\\derive-character-stage-sections.ts", "source_location": "L134"}, {"caller_nid": "derive_character_stage_sections_joinpreviewvalues", "callee": "push", "source_file": "src\\renderer\\src\\features\\character\\model\\derive-character-stage-sections.ts", "source_location": "L135"}, {"caller_nid": "derive_character_stage_sections_joinpreviewvalues", "callee": "join", "source_file": "src\\renderer\\src\\features\\character\\model\\derive-character-stage-sections.ts", "source_location": "L138"}, {"caller_nid": "derive_character_stage_sections_buildfactionplaceholderseats", "callee": "map", "source_file": "src\\renderer\\src\\features\\character\\model\\derive-character-stage-sections.ts", "source_location": "L155"}, {"caller_nid": "derive_character_stage_sections_buildfactionplaceholderseats", "callee": "filter", "source_file": "src\\renderer\\src\\features\\character\\model\\derive-character-stage-sections.ts", "source_location": "L155"}, {"caller_nid": "derive_character_stage_sections_buildfactionplaceholderseats", "callee": "buildFactionSeatBlueprints", "source_file": "src\\renderer\\src\\features\\character\\model\\derive-character-stage-sections.ts", "source_location": "L155"}, {"caller_nid": "derive_character_stage_sections_buildfactionslotseats", "callee": "map", "source_file": "src\\renderer\\src\\features\\character\\model\\derive-character-stage-sections.ts", "source_location": "L176"}, {"caller_nid": "derive_character_stage_sections_buildfactionslotseats", "callee": "sort", "source_file": "src\\renderer\\src\\features\\character\\model\\derive-character-stage-sections.ts", "source_location": "L176"}, {"caller_nid": "derive_character_stage_sections_buildfactionslotseats", "callee": "filter", "source_file": "src\\renderer\\src\\features\\character\\model\\derive-character-stage-sections.ts", "source_location": "L176"}, {"caller_nid": "derive_character_stage_sections_resolvefullprofileentityids", "callee": "resolveMasterEntityId", "source_file": "src\\renderer\\src\\features\\character\\model\\derive-character-stage-sections.ts", "source_location": "L199"}, {"caller_nid": "derive_character_stage_sections_resolvefullprofileentityids", "callee": "add", "source_file": "src\\renderer\\src\\features\\character\\model\\derive-character-stage-sections.ts", "source_location": "L201"}, {"caller_nid": "derive_character_stage_sections_resolvefullprofileentityids", "callee": "findCharacterEntityByName", "source_file": "src\\renderer\\src\\features\\character\\model\\derive-character-stage-sections.ts", "source_location": "L204"}, {"caller_nid": "derive_character_stage_sections_resolvefullprofileentityids", "callee": "add", "source_file": "src\\renderer\\src\\features\\character\\model\\derive-character-stage-sections.ts", "source_location": "L206"}, {"caller_nid": "derive_character_stage_sections_resolvefullprofileentityids", "callee": "some", "source_file": "src\\renderer\\src\\features\\character\\model\\derive-character-stage-sections.ts", "source_location": "L212"}, {"caller_nid": "derive_character_stage_sections_resolvefullprofileentityids", "callee": "add", "source_file": "src\\renderer\\src\\features\\character\\model\\derive-character-stage-sections.ts", "source_location": "L214"}, {"caller_nid": "derive_character_stage_sections_buildlightcards", "callee": "map", "source_file": "src\\renderer\\src\\features\\character\\model\\derive-character-stage-sections.ts", "source_location": "L227"}, {"caller_nid": "derive_character_stage_sections_buildlightcards", "callee": "map", "source_file": "src\\renderer\\src\\features\\character\\model\\derive-character-stage-sections.ts", "source_location": "L229"}, {"caller_nid": "derive_character_stage_sections_buildlightcards", "callee": "sort", "source_file": "src\\renderer\\src\\features\\character\\model\\derive-character-stage-sections.ts", "source_location": "L229"}, {"caller_nid": "derive_character_stage_sections_buildlightcards", "callee": "filter", "source_file": "src\\renderer\\src\\features\\character\\model\\derive-character-stage-sections.ts", "source_location": "L229"}, {"caller_nid": "derive_character_stage_sections_buildlightcards", "callee": "slice", "source_file": "src\\renderer\\src\\features\\character\\model\\derive-character-stage-sections.ts", "source_location": "L253"}, {"caller_nid": "derive_character_stage_sections_buildlightcards", "callee": "max", "source_file": "src\\renderer\\src\\features\\character\\model\\derive-character-stage-sections.ts", "source_location": "L253"}, {"caller_nid": "derive_character_stage_sections_buildfactionroster", "callee": "map", "source_file": "src\\renderer\\src\\features\\character\\model\\derive-character-stage-sections.ts", "source_location": "L264"}, {"caller_nid": "derive_character_stage_sections_buildfactionroster", "callee": "filter", "source_file": "src\\renderer\\src\\features\\character\\model\\derive-character-stage-sections.ts", "source_location": "L264"}, {"caller_nid": "derive_character_stage_sections_buildfactionroster", "callee": "map", "source_file": "src\\renderer\\src\\features\\character\\model\\derive-character-stage-sections.ts", "source_location": "L269"}, {"caller_nid": "derive_character_stage_sections_buildcharacterstagesections", "callee": "max", "source_file": "src\\renderer\\src\\features\\character\\model\\derive-character-stage-sections.ts", "source_location": "L315"}, {"caller_nid": "derive_character_stage_sections_buildcharacterstagesections", "callee": "reduce", "source_file": "src\\renderer\\src\\features\\character\\model\\derive-character-stage-sections.ts", "source_location": "L321"}, {"caller_nid": "derive_character_stage_sections_createcharacterdraftfromentitystore", "callee": "find", "source_file": "src\\renderer\\src\\features\\character\\model\\derive-character-stage-sections.ts", "source_location": "L330"}, {"caller_nid": "derive_character_stage_sections_createcharacterdraftfromentitystore", "callee": "fromMasterEntity", "source_file": "src\\renderer\\src\\features\\character\\model\\derive-character-stage-sections.ts", "source_location": "L334"}]}