{"nodes": [{"id": "src_renderer_src_app_store_useworkflowstore_test_ts", "label": "useWorkflowStore.test.ts", "file_type": "code", "source_file": "src\\renderer\\src\\app\\store\\useWorkflowStore.test.ts", "source_location": "L1"}, {"id": "useworkflowstore_test_createprojectsnapshot", "label": "createProjectSnapshot()", "file_type": "code", "source_file": "src\\renderer\\src\\app\\store\\useWorkflowStore.test.ts", "source_location": "L8"}, {"id": "useworkflowstore_test_resetworkflowstore", "label": "resetWorkflowStore()", "file_type": "code", "source_file": "src\\renderer\\src\\app\\store\\useWorkflowStore.test.ts", "source_location": "L150"}], "edges": [{"source": "src_renderer_src_app_store_useworkflowstore_test_ts", "target": "node_test", "relation": "imports_from", "confidence": "EXTRACTED", "source_file": "src\\renderer\\src\\app\\store\\useWorkflowStore.test.ts", "source_location": "L1", "weight": 1.0}, {"source": "src_renderer_src_app_store_useworkflowstore_test_ts", "target": "strict", "relation": "imports_from", "confidence": "EXTRACTED", "source_file": "src\\renderer\\src\\app\\store\\useWorkflowStore.test.ts", "source_location": "L2", "weight": 1.0}, {"source": "src_renderer_src_app_store_useworkflowstore_test_ts", "target": "src_shared_contracts_project_ts", "relation": "imports_from", "confidence": "EXTRACTED", "source_file": "src\\renderer\\src\\app\\store\\useWorkflowStore.test.ts", "source_location": "L4", "weight": 1.0}, {"source": "src_renderer_src_app_store_useworkflowstore_test_ts", "target": "src_renderer_src_app_store_useworkflowstore_ts", "relation": "imports_from", "confidence": "EXTRACTED", "source_file": "src\\renderer\\src\\app\\store\\useWorkflowStore.test.ts", "source_location": "L5", "weight": 1.0}, {"source": "src_renderer_src_app_store_useworkflowstore_test_ts", "target": "src_renderer_src_store_usestagestore_ts", "relation": "imports_from", "confidence": "EXTRACTED", "source_file": "src\\renderer\\src\\app\\store\\useWorkflowStore.test.ts", "source_location": "L6", "weight": 1.0}, {"source": "src_renderer_src_app_store_useworkflowstore_test_ts", "target": "useworkflowstore_test_createprojectsnapshot", "relation": "contains", "confidence": "EXTRACTED", "source_file": "src\\renderer\\src\\app\\store\\useWorkflowStore.test.ts", "source_location": "L8", "weight": 1.0}, {"source": "src_renderer_src_app_store_useworkflowstore_test_ts", "target": "useworkflowstore_test_resetworkflowstore", "relation": "contains", "confidence": "EXTRACTED", "source_file": "src\\renderer\\src\\app\\store\\useWorkflowStore.test.ts", "source_location": "L150", "weight": 1.0}], "raw_calls": [{"caller_nid": "useworkflowstore_test_createprojectsnapshot", "callee": "now", "source_file": "src\\renderer\\src\\app\\store\\useWorkflowStore.test.ts", "source_location": "L17"}, {"caller_nid": "useworkflowstore_test_createprojectsnapshot", "callee": "now", "source_file": "src\\renderer\\src\\app\\store\\useWorkflowStore.test.ts", "source_location": "L23"}, {"caller_nid": "useworkflowstore_test_resetworkflowstore", "callee": "reset", "source_file": "src\\renderer\\src\\app\\store\\useWorkflowStore.test.ts", "source_location": "L151"}, {"caller_nid": "useworkflowstore_test_resetworkflowstore", "callee": "getState", "source_file": "src\\renderer\\src\\app\\store\\useWorkflowStore.test.ts", "source_location": "L151"}, {"caller_nid": "useworkflowstore_test_resetworkflowstore", "callee": "reset", "source_file": "src\\renderer\\src\\app\\store\\useWorkflowStore.test.ts", "source_location": "L152"}, {"caller_nid": "useworkflowstore_test_resetworkflowstore", "callee": "getState", "source_file": "src\\renderer\\src\\app\\store\\useWorkflowStore.test.ts", "source_location": "L152"}]}