{"nodes": [{"id": "src_main_infrastructure_storage_project_store_migration_ts", "label": "project-store-migration.ts", "file_type": "code", "source_file": "src\\main\\infrastructure\\storage\\project-store-migration.ts", "source_location": "L1"}, {"id": "project_store_migration_shouldpreferricherbackup", "label": "shouldPreferRicherBackup()", "file_type": "code", "source_file": "src\\main\\infrastructure\\storage\\project-store-migration.ts", "source_location": "L18"}, {"id": "project_store_migration_countprojectsfromstoreraw", "label": "countProjectsFromStoreRaw()", "file_type": "code", "source_file": "src\\main\\infrastructure\\storage\\project-store-migration.ts", "source_location": "L37"}, {"id": "project_store_migration_readstoremeta", "label": "readStoreMeta()", "file_type": "code", "source_file": "src\\main\\infrastructure\\storage\\project-store-migration.ts", "source_location": "L47"}, {"id": "project_store_migration_getlegacyelectronstorepath", "label": "getLegacyElectronStorePath()", "file_type": "code", "source_file": "src\\main\\infrastructure\\storage\\project-store-migration.ts", "source_location": "L70"}, {"id": "project_store_migration_listcorruptbackuppaths", "label": "listCorruptBackupPaths()", "file_type": "code", "source_file": "src\\main\\infrastructure\\storage\\project-store-migration.ts", "source_location": "L82"}, {"id": "project_store_migration_createautobackup", "label": "createAutoBackup()", "file_type": "code", "source_file": "src\\main\\infrastructure\\storage\\project-store-migration.ts", "source_location": "L90"}, {"id": "project_store_migration_migratelegacyelectronstoreifneeded", "label": "migrateLegacyElectronStoreIfNeeded()", "file_type": "code", "source_file": "src\\main\\infrastructure\\storage\\project-store-migration.ts", "source_location": "L100"}, {"id": "project_store_migration_recovercorruptprojectstoreifneeded", "label": "recoverCorruptProjectStoreIfNeeded()", "file_type": "code", "source_file": "src\\main\\infrastructure\\storage\\project-store-migration.ts", "source_location": "L125"}], "edges": [{"source": "src_main_infrastructure_storage_project_store_migration_ts", "target": "path", "relation": "imports_from", "confidence": "EXTRACTED", "source_file": "src\\main\\infrastructure\\storage\\project-store-migration.ts", "source_location": "L1", "weight": 1.0}, {"source": "src_main_infrastructure_storage_project_store_migration_ts", "target": "promises", "relation": "imports_from", "confidence": "EXTRACTED", "source_file": "src\\main\\infrastructure\\storage\\project-store-migration.ts", "source_location": "L2", "weight": 1.0}, {"source": "src_main_infrastructure_storage_project_store_migration_ts", "target": "project_store_migration_shouldpreferricherbackup", "relation": "contains", "confidence": "EXTRACTED", "source_file": "src\\main\\infrastructure\\storage\\project-store-migration.ts", "source_location": "L18", "weight": 1.0}, {"source": "src_main_infrastructure_storage_project_store_migration_ts", "target": "project_store_migration_countprojectsfromstoreraw", "relation": "contains", "confidence": "EXTRACTED", "source_file": "src\\main\\infrastructure\\storage\\project-store-migration.ts", "source_location": "L37", "weight": 1.0}, {"source": "src_main_infrastructure_storage_project_store_migration_ts", "target": "project_store_migration_readstoremeta", "relation": "contains", "confidence": "EXTRACTED", "source_file": "src\\main\\infrastructure\\storage\\project-store-migration.ts", "source_location": "L47", "weight": 1.0}, {"source": "src_main_infrastructure_storage_project_store_migration_ts", "target": "project_store_migration_getlegacyelectronstorepath", "relation": "contains", "confidence": "EXTRACTED", "source_file": "src\\main\\infrastructure\\storage\\project-store-migration.ts", "source_location": "L70", "weight": 1.0}, {"source": "src_main_infrastructure_storage_project_store_migration_ts", "target": "project_store_migration_listcorruptbackuppaths", "relation": "contains", "confidence": "EXTRACTED", "source_file": "src\\main\\infrastructure\\storage\\project-store-migration.ts", "source_location": "L82", "weight": 1.0}, {"source": "src_main_infrastructure_storage_project_store_migration_ts", "target": "project_store_migration_createautobackup", "relation": "contains", "confidence": "EXTRACTED", "source_file": "src\\main\\infrastructure\\storage\\project-store-migration.ts", "source_location": "L90", "weight": 1.0}, {"source": "src_main_infrastructure_storage_project_store_migration_ts", "target": "project_store_migration_migratelegacyelectronstoreifneeded", "relation": "contains", "confidence": "EXTRACTED", "source_file": "src\\main\\infrastructure\\storage\\project-store-migration.ts", "source_location": "L100", "weight": 1.0}, {"source": "src_main_infrastructure_storage_project_store_migration_ts", "target": "project_store_migration_recovercorruptprojectstoreifneeded", "relation": "contains", "confidence": "EXTRACTED", "source_file": "src\\main\\infrastructure\\storage\\project-store-migration.ts", "source_location": "L125", "weight": 1.0}, {"source": "project_store_migration_readstoremeta", "target": "project_store_migration_countprojectsfromstoreraw", "relation": "calls", "confidence": "EXTRACTED", "source_file": "src\\main\\infrastructure\\storage\\project-store-migration.ts", "source_location": "L53", "weight": 1.0}, {"source": "project_store_migration_migratelegacyelectronstoreifneeded", "target": "project_store_migration_getlegacyelectronstorepath", "relation": "calls", "confidence": "EXTRACTED", "source_file": "src\\main\\infrastructure\\storage\\project-store-migration.ts", "source_location": "L105", "weight": 1.0}, {"source": "project_store_migration_migratelegacyelectronstoreifneeded", "target": "project_store_migration_countprojectsfromstoreraw", "relation": "calls", "confidence": "EXTRACTED", "source_file": "src\\main\\infrastructure\\storage\\project-store-migration.ts", "source_location": "L109", "weight": 1.0}, {"source": "project_store_migration_recovercorruptprojectstoreifneeded", "target": "project_store_migration_readstoremeta", "relation": "calls", "confidence": "EXTRACTED", "source_file": "src\\main\\infrastructure\\storage\\project-store-migration.ts", "source_location": "L133", "weight": 1.0}, {"source": "project_store_migration_recovercorruptprojectstoreifneeded", "target": "project_store_migration_getlegacyelectronstorepath", "relation": "calls", "confidence": "EXTRACTED", "source_file": "src\\main\\infrastructure\\storage\\project-store-migration.ts", "source_location": "L134", "weight": 1.0}, {"source": "project_store_migration_recovercorruptprojectstoreifneeded", "target": "project_store_migration_listcorruptbackuppaths", "relation": "calls", "confidence": "EXTRACTED", "source_file": "src\\main\\infrastructure\\storage\\project-store-migration.ts", "source_location": "L140", "weight": 1.0}, {"source": "project_store_migration_recovercorruptprojectstoreifneeded", "target": "project_store_migration_shouldpreferricherbackup", "relation": "calls", "confidence": "EXTRACTED", "source_file": "src\\main\\infrastructure\\storage\\project-store-migration.ts", "source_location": "L177", "weight": 1.0}, {"source": "project_store_migration_recovercorruptprojectstoreifneeded", "target": "project_store_migration_createautobackup", "relation": "calls", "confidence": "EXTRACTED", "source_file": "src\\main\\infrastructure\\storage\\project-store-migration.ts", "source_location": "L184", "weight": 1.0}], "raw_calls": [{"caller_nid": "project_store_migration_shouldpreferricherbackup", "callee": "trim", "source_file": "src\\main\\infrastructure\\storage\\project-store-migration.ts", "source_location": "L25"}, {"caller_nid": "project_store_migration_shouldpreferricherbackup", "callee": "trim", "source_file": "src\\main\\infrastructure\\storage\\project-store-migration.ts", "source_location": "L26"}, {"caller_nid": "project_store_migration_shouldpreferricherbackup", "callee": "max", "source_file": "src\\main\\infrastructure\\storage\\project-store-migration.ts", "source_location": "L33"}, {"caller_nid": "project_store_migration_countprojectsfromstoreraw", "callee": "trim", "source_file": "src\\main\\infrastructure\\storage\\project-store-migration.ts", "source_location": "L38"}, {"caller_nid": "project_store_migration_countprojectsfromstoreraw", "callee": "parse", "source_file": "src\\main\\infrastructure\\storage\\project-store-migration.ts", "source_location": "L40"}, {"caller_nid": "project_store_migration_countprojectsfromstoreraw", "callee": "keys", "source_file": "src\\main\\infrastructure\\storage\\project-store-migration.ts", "source_location": "L41"}, {"caller_nid": "project_store_migration_readstoremeta", "callee": "all", "source_file": "src\\main\\infrastructure\\storage\\project-store-migration.ts", "source_location": "L48"}, {"caller_nid": "project_store_migration_readstoremeta", "callee": "catch", "source_file": "src\\main\\infrastructure\\storage\\project-store-migration.ts", "source_location": "L49"}, {"caller_nid": "project_store_migration_readstoremeta", "callee": "readFile", "source_file": "src\\main\\infrastructure\\storage\\project-store-migration.ts", "source_location": "L49"}, {"caller_nid": "project_store_migration_readstoremeta", "callee": "catch", "source_file": "src\\main\\infrastructure\\storage\\project-store-migration.ts", "source_location": "L50"}, {"caller_nid": "project_store_migration_readstoremeta", "callee": "stat", "source_file": "src\\main\\infrastructure\\storage\\project-store-migration.ts", "source_location": "L50"}, {"caller_nid": "project_store_migration_readstoremeta", "callee": "trim", "source_file": "src\\main\\infrastructure\\storage\\project-store-migration.ts", "source_location": "L54"}, {"caller_nid": "project_store_migration_readstoremeta", "callee": "(() => {\n          try {\n            JSON.parse(raw)\n            return true\n          } catch {\n            return false\n          }\n        })", "source_file": "src\\main\\infrastructure\\storage\\project-store-migration.ts", "source_location": "L56"}, {"caller_nid": "project_store_migration_getlegacyelectronstorepath", "callee": "dirname", "source_file": "src\\main\\infrastructure\\storage\\project-store-migration.ts", "source_location": "L76"}, {"caller_nid": "project_store_migration_getlegacyelectronstorepath", "callee": "dirname", "source_file": "src\\main\\infrastructure\\storage\\project-store-migration.ts", "source_location": "L76"}, {"caller_nid": "project_store_migration_getlegacyelectronstorepath", "callee": "join", "source_file": "src\\main\\infrastructure\\storage\\project-store-migration.ts", "source_location": "L77"}, {"caller_nid": "project_store_migration_getlegacyelectronstorepath", "callee": "join", "source_file": "src\\main\\infrastructure\\storage\\project-store-migration.ts", "source_location": "L79"}, {"caller_nid": "project_store_migration_listcorruptbackuppaths", "callee": "dirname", "source_file": "src\\main\\infrastructure\\storage\\project-store-migration.ts", "source_location": "L83"}, {"caller_nid": "project_store_migration_listcorruptbackuppaths", "callee": "catch", "source_file": "src\\main\\infrastructure\\storage\\project-store-migration.ts", "source_location": "L84"}, {"caller_nid": "project_store_migration_listcorruptbackuppaths", "callee": "readdir", "source_file": "src\\main\\infrastructure\\storage\\project-store-migration.ts", "source_location": "L84"}, {"caller_nid": "project_store_migration_listcorruptbackuppaths", "callee": "map", "source_file": "src\\main\\infrastructure\\storage\\project-store-migration.ts", "source_location": "L85"}, {"caller_nid": "project_store_migration_listcorruptbackuppaths", "callee": "filter", "source_file": "src\\main\\infrastructure\\storage\\project-store-migration.ts", "source_location": "L85"}, {"caller_nid": "project_store_migration_createautobackup", "callee": "catch", "source_file": "src\\main\\infrastructure\\storage\\project-store-migration.ts", "source_location": "L91"}, {"caller_nid": "project_store_migration_createautobackup", "callee": "readFile", "source_file": "src\\main\\infrastructure\\storage\\project-store-migration.ts", "source_location": "L91"}, {"caller_nid": "project_store_migration_createautobackup", "callee": "trim", "source_file": "src\\main\\infrastructure\\storage\\project-store-migration.ts", "source_location": "L92"}, {"caller_nid": "project_store_migration_createautobackup", "callee": "replace", "source_file": "src\\main\\infrastructure\\storage\\project-store-migration.ts", "source_location": "L93"}, {"caller_nid": "project_store_migration_createautobackup", "callee": "toString", "source_file": "src\\main\\infrastructure\\storage\\project-store-migration.ts", "source_location": "L95"}, {"caller_nid": "project_store_migration_createautobackup", "callee": "now", "source_file": "src\\main\\infrastructure\\storage\\project-store-migration.ts", "source_location": "L95"}, {"caller_nid": "project_store_migration_createautobackup", "callee": "catch", "source_file": "src\\main\\infrastructure\\storage\\project-store-migration.ts", "source_location": "L97"}, {"caller_nid": "project_store_migration_createautobackup", "callee": "copyFile", "source_file": "src\\main\\infrastructure\\storage\\project-store-migration.ts", "source_location": "L97"}, {"caller_nid": "project_store_migration_migratelegacyelectronstoreifneeded", "callee": "catch", "source_file": "src\\main\\infrastructure\\storage\\project-store-migration.ts", "source_location": "L108"}, {"caller_nid": "project_store_migration_migratelegacyelectronstoreifneeded", "callee": "readFile", "source_file": "src\\main\\infrastructure\\storage\\project-store-migration.ts", "source_location": "L108"}, {"caller_nid": "project_store_migration_migratelegacyelectronstoreifneeded", "callee": "catch", "source_file": "src\\main\\infrastructure\\storage\\project-store-migration.ts", "source_location": "L111"}, {"caller_nid": "project_store_migration_migratelegacyelectronstoreifneeded", "callee": "readFile", "source_file": "src\\main\\infrastructure\\storage\\project-store-migration.ts", "source_location": "L111"}, {"caller_nid": "project_store_migration_migratelegacyelectronstoreifneeded", "callee": "writeFile", "source_file": "src\\main\\infrastructure\\storage\\project-store-migration.ts", "source_location": "L115"}, {"caller_nid": "project_store_migration_migratelegacyelectronstoreifneeded", "callee": "log", "source_file": "src\\main\\infrastructure\\storage\\project-store-migration.ts", "source_location": "L118"}, {"caller_nid": "project_store_migration_recovercorruptprojectstoreifneeded", "callee": "replace", "source_file": "src\\main\\infrastructure\\storage\\project-store-migration.ts", "source_location": "L143"}, {"caller_nid": "project_store_migration_recovercorruptprojectstoreifneeded", "callee": "toString", "source_file": "src\\main\\infrastructure\\storage\\project-store-migration.ts", "source_location": "L145"}, {"caller_nid": "project_store_migration_recovercorruptprojectstoreifneeded", "callee": "now", "source_file": "src\\main\\infrastructure\\storage\\project-store-migration.ts", "source_location": "L145"}, {"caller_nid": "project_store_migration_recovercorruptprojectstoreifneeded", "callee": "catch", "source_file": "src\\main\\infrastructure\\storage\\project-store-migration.ts", "source_location": "L147"}, {"caller_nid": "project_store_migration_recovercorruptprojectstoreifneeded", "callee": "rename", "source_file": "src\\main\\infrastructure\\storage\\project-store-migration.ts", "source_location": "L147"}, {"caller_nid": "project_store_migration_recovercorruptprojectstoreifneeded", "callee": "all", "source_file": "src\\main\\infrastructure\\storage\\project-store-migration.ts", "source_location": "L150"}, {"caller_nid": "project_store_migration_recovercorruptprojectstoreifneeded", "callee": "map", "source_file": "src\\main\\infrastructure\\storage\\project-store-migration.ts", "source_location": "L151"}, {"caller_nid": "project_store_migration_recovercorruptprojectstoreifneeded", "callee": "sort", "source_file": "src\\main\\infrastructure\\storage\\project-store-migration.ts", "source_location": "L156"}, {"caller_nid": "project_store_migration_recovercorruptprojectstoreifneeded", "callee": "filter", "source_file": "src\\main\\infrastructure\\storage\\project-store-migration.ts", "source_location": "L156"}, {"caller_nid": "project_store_migration_recovercorruptprojectstoreifneeded", "callee": "readFile", "source_file": "src\\main\\infrastructure\\storage\\project-store-migration.ts", "source_location": "L185"}, {"caller_nid": "project_store_migration_recovercorruptprojectstoreifneeded", "callee": "writeFile", "source_file": "src\\main\\infrastructure\\storage\\project-store-migration.ts", "source_location": "L186"}, {"caller_nid": "project_store_migration_recovercorruptprojectstoreifneeded", "callee": "warn", "source_file": "src\\main\\infrastructure\\storage\\project-store-migration.ts", "source_location": "L189"}]}