{"nodes": [{"id": "src_shared_contracts_script_generation_contract_ts", "label": "script-generation-contract.ts", "file_type": "code", "source_file": "src\\shared\\contracts\\script-generation-contract.ts", "source_location": "L1"}], "edges": [{"source": "src_shared_contracts_script_generation_contract_ts", "target": "src_shared_contracts_story_contract", "relation": "imports_from", "confidence": "EXTRACTED", "source_file": "src\\shared\\contracts\\script-generation-contract.ts", "source_location": "L1", "weight": 1.0}], "raw_calls": []}