{"nodes": [{"id": "src_main_application_script_generation_prompt_create_scene_generation_prompt_ts", "label": "create-scene-generation-prompt.ts", "file_type": "code", "source_file": "src\\main\\application\\script-generation\\prompt\\create-scene-generation-prompt.ts", "source_location": "L1"}, {"id": "create_scene_generation_prompt_createscenegenerationprompt", "label": "createSceneGenerationPrompt()", "file_type": "code", "source_file": "src\\main\\application\\script-generation\\prompt\\create-scene-generation-prompt.ts", "source_location": "L106"}, {"id": "create_scene_generation_prompt_assemblescenesforepisode", "label": "assembleScenesForEpisode()", "file_type": "code", "source_file": "src\\main\\application\\script-generation\\prompt\\create-scene-generation-prompt.ts", "source_location": "L180"}], "edges": [{"source": "src_main_application_script_generation_prompt_create_scene_generation_prompt_ts", "target": "create_scene_generation_prompt_createscenegenerationprompt", "relation": "contains", "confidence": "EXTRACTED", "source_file": "src\\main\\application\\script-generation\\prompt\\create-scene-generation-prompt.ts", "source_location": "L106", "weight": 1.0}, {"source": "src_main_application_script_generation_prompt_create_scene_generation_prompt_ts", "target": "create_scene_generation_prompt_assemblescenesforepisode", "relation": "contains", "confidence": "EXTRACTED", "source_file": "src\\main\\application\\script-generation\\prompt\\create-scene-generation-prompt.ts", "source_location": "L180", "weight": 1.0}], "raw_calls": [{"caller_nid": "create_scene_generation_prompt_createscenegenerationprompt", "callee": "push", "source_file": "src\\main\\application\\script-generation\\prompt\\create-scene-generation-prompt.ts", "source_location": "L110"}, {"caller_nid": "create_scene_generation_prompt_createscenegenerationprompt", "callee": "push", "source_file": "src\\main\\application\\script-generation\\prompt\\create-scene-generation-prompt.ts", "source_location": "L113"}, {"caller_nid": "create_scene_generation_prompt_createscenegenerationprompt", "callee": "push", "source_file": "src\\main\\application\\script-generation\\prompt\\create-scene-generation-prompt.ts", "source_location": "L114"}, {"caller_nid": "create_scene_generation_prompt_createscenegenerationprompt", "callee": "push", "source_file": "src\\main\\application\\script-generation\\prompt\\create-scene-generation-prompt.ts", "source_location": "L115"}, {"caller_nid": "create_scene_generation_prompt_createscenegenerationprompt", "callee": "push", "source_file": "src\\main\\application\\script-generation\\prompt\\create-scene-generation-prompt.ts", "source_location": "L116"}, {"caller_nid": "create_scene_generation_prompt_createscenegenerationprompt", "callee": "join", "source_file": "src\\main\\application\\script-generation\\prompt\\create-scene-generation-prompt.ts", "source_location": "L116"}, {"caller_nid": "create_scene_generation_prompt_createscenegenerationprompt", "callee": "push", "source_file": "src\\main\\application\\script-generation\\prompt\\create-scene-generation-prompt.ts", "source_location": "L117"}, {"caller_nid": "create_scene_generation_prompt_createscenegenerationprompt", "callee": "push", "source_file": "src\\main\\application\\script-generation\\prompt\\create-scene-generation-prompt.ts", "source_location": "L118"}, {"caller_nid": "create_scene_generation_prompt_createscenegenerationprompt", "callee": "push", "source_file": "src\\main\\application\\script-generation\\prompt\\create-scene-generation-prompt.ts", "source_location": "L119"}, {"caller_nid": "create_scene_generation_prompt_createscenegenerationprompt", "callee": "push", "source_file": "src\\main\\application\\script-generation\\prompt\\create-scene-generation-prompt.ts", "source_location": "L120"}, {"caller_nid": "create_scene_generation_prompt_createscenegenerationprompt", "callee": "push", "source_file": "src\\main\\application\\script-generation\\prompt\\create-scene-generation-prompt.ts", "source_location": "L126"}, {"caller_nid": "create_scene_generation_prompt_createscenegenerationprompt", "callee": "replace", "source_file": "src\\main\\application\\script-generation\\prompt\\create-scene-generation-prompt.ts", "source_location": "L126"}, {"caller_nid": "create_scene_generation_prompt_createscenegenerationprompt", "callee": "String", "source_file": "src\\main\\application\\script-generation\\prompt\\create-scene-generation-prompt.ts", "source_location": "L126"}, {"caller_nid": "create_scene_generation_prompt_createscenegenerationprompt", "callee": "push", "source_file": "src\\main\\application\\script-generation\\prompt\\create-scene-generation-prompt.ts", "source_location": "L131"}, {"caller_nid": "create_scene_generation_prompt_createscenegenerationprompt", "callee": "replace", "source_file": "src\\main\\application\\script-generation\\prompt\\create-scene-generation-prompt.ts", "source_location": "L131"}, {"caller_nid": "create_scene_generation_prompt_createscenegenerationprompt", "callee": "replace", "source_file": "src\\main\\application\\script-generation\\prompt\\create-scene-generation-prompt.ts", "source_location": "L131"}, {"caller_nid": "create_scene_generation_prompt_createscenegenerationprompt", "callee": "push", "source_file": "src\\main\\application\\script-generation\\prompt\\create-scene-generation-prompt.ts", "source_location": "L136"}, {"caller_nid": "create_scene_generation_prompt_createscenegenerationprompt", "callee": "push", "source_file": "src\\main\\application\\script-generation\\prompt\\create-scene-generation-prompt.ts", "source_location": "L139"}, {"caller_nid": "create_scene_generation_prompt_createscenegenerationprompt", "callee": "push", "source_file": "src\\main\\application\\script-generation\\prompt\\create-scene-generation-prompt.ts", "source_location": "L144"}, {"caller_nid": "create_scene_generation_prompt_createscenegenerationprompt", "callee": "push", "source_file": "src\\main\\application\\script-generation\\prompt\\create-scene-generation-prompt.ts", "source_location": "L151"}, {"caller_nid": "create_scene_generation_prompt_createscenegenerationprompt", "callee": "push", "source_file": "src\\main\\application\\script-generation\\prompt\\create-scene-generation-prompt.ts", "source_location": "L153"}, {"caller_nid": "create_scene_generation_prompt_createscenegenerationprompt", "callee": "push", "source_file": "src\\main\\application\\script-generation\\prompt\\create-scene-generation-prompt.ts", "source_location": "L156"}, {"caller_nid": "create_scene_generation_prompt_createscenegenerationprompt", "callee": "push", "source_file": "src\\main\\application\\script-generation\\prompt\\create-scene-generation-prompt.ts", "source_location": "L158"}, {"caller_nid": "create_scene_generation_prompt_createscenegenerationprompt", "callee": "push", "source_file": "src\\main\\application\\script-generation\\prompt\\create-scene-generation-prompt.ts", "source_location": "L160"}, {"caller_nid": "create_scene_generation_prompt_createscenegenerationprompt", "callee": "push", "source_file": "src\\main\\application\\script-generation\\prompt\\create-scene-generation-prompt.ts", "source_location": "L161"}, {"caller_nid": "create_scene_generation_prompt_createscenegenerationprompt", "callee": "push", "source_file": "src\\main\\application\\script-generation\\prompt\\create-scene-generation-prompt.ts", "source_location": "L165"}, {"caller_nid": "create_scene_generation_prompt_createscenegenerationprompt", "callee": "push", "source_file": "src\\main\\application\\script-generation\\prompt\\create-scene-generation-prompt.ts", "source_location": "L166"}, {"caller_nid": "create_scene_generation_prompt_createscenegenerationprompt", "callee": "join", "source_file": "src\\main\\application\\script-generation\\prompt\\create-scene-generation-prompt.ts", "source_location": "L168"}, {"caller_nid": "create_scene_generation_prompt_assemblescenesforepisode", "callee": "push", "source_file": "src\\main\\application\\script-generation\\prompt\\create-scene-generation-prompt.ts", "source_location": "L183"}, {"caller_nid": "create_scene_generation_prompt_assemblescenesforepisode", "callee": "trim", "source_file": "src\\main\\application\\script-generation\\prompt\\create-scene-generation-prompt.ts", "source_location": "L183"}, {"caller_nid": "create_scene_generation_prompt_assemblescenesforepisode", "callee": "push", "source_file": "src\\main\\application\\script-generation\\prompt\\create-scene-generation-prompt.ts", "source_location": "L184"}, {"caller_nid": "create_scene_generation_prompt_assemblescenesforepisode", "callee": "trim", "source_file": "src\\main\\application\\script-generation\\prompt\\create-scene-generation-prompt.ts", "source_location": "L186"}, {"caller_nid": "create_scene_generation_prompt_assemblescenesforepisode", "callee": "join", "source_file": "src\\main\\application\\script-generation\\prompt\\create-scene-generation-prompt.ts", "source_location": "L186"}]}