{"nodes": [{"id": "src_main_application_script_generation_ledger_ledger_scene_summary_ts", "label": "ledger-scene-summary.ts", "file_type": "code", "source_file": "src\\main\\application\\script-generation\\ledger\\ledger-scene-summary.ts", "source_location": "L1"}, {"id": "ledger_scene_summary_cliptext", "label": "clipText()", "file_type": "code", "source_file": "src\\main\\application\\script-generation\\ledger\\ledger-scene-summary.ts", "source_location": "L3"}, {"id": "ledger_scene_summary_picksummarylines", "label": "pickSummaryLines()", "file_type": "code", "source_file": "src\\main\\application\\script-generation\\ledger\\ledger-scene-summary.ts", "source_location": "L12"}, {"id": "ledger_scene_summary_summarizescenefragment", "label": "summarizeSceneFragment()", "file_type": "code", "source_file": "src\\main\\application\\script-generation\\ledger\\ledger-scene-summary.ts", "source_location": "L23"}], "edges": [{"source": "src_main_application_script_generation_ledger_ledger_scene_summary_ts", "target": "src_shared_contracts_workflow", "relation": "imports_from", "confidence": "EXTRACTED", "source_file": "src\\main\\application\\script-generation\\ledger\\ledger-scene-summary.ts", "source_location": "L1", "weight": 1.0}, {"source": "src_main_application_script_generation_ledger_ledger_scene_summary_ts", "target": "ledger_scene_summary_cliptext", "relation": "contains", "confidence": "EXTRACTED", "source_file": "src\\main\\application\\script-generation\\ledger\\ledger-scene-summary.ts", "source_location": "L3", "weight": 1.0}, {"source": "src_main_application_script_generation_ledger_ledger_scene_summary_ts", "target": "ledger_scene_summary_picksummarylines", "relation": "contains", "confidence": "EXTRACTED", "source_file": "src\\main\\application\\script-generation\\ledger\\ledger-scene-summary.ts", "source_location": "L12", "weight": 1.0}, {"source": "src_main_application_script_generation_ledger_ledger_scene_summary_ts", "target": "ledger_scene_summary_summarizescenefragment", "relation": "contains", "confidence": "EXTRACTED", "source_file": "src\\main\\application\\script-generation\\ledger\\ledger-scene-summary.ts", "source_location": "L23", "weight": 1.0}, {"source": "ledger_scene_summary_summarizescenefragment", "target": "ledger_scene_summary_cliptext", "relation": "calls", "confidence": "EXTRACTED", "source_file": "src\\main\\application\\script-generation\\ledger\\ledger-scene-summary.ts", "source_location": "L42", "weight": 1.0}, {"source": "ledger_scene_summary_summarizescenefragment", "target": "ledger_scene_summary_picksummarylines", "relation": "calls", "confidence": "EXTRACTED", "source_file": "src\\main\\application\\script-generation\\ledger\\ledger-scene-summary.ts", "source_location": "L44", "weight": 1.0}], "raw_calls": [{"caller_nid": "ledger_scene_summary_cliptext", "callee": "trim", "source_file": "src\\main\\application\\script-generation\\ledger\\ledger-scene-summary.ts", "source_location": "L4"}, {"caller_nid": "ledger_scene_summary_cliptext", "callee": "replace", "source_file": "src\\main\\application\\script-generation\\ledger\\ledger-scene-summary.ts", "source_location": "L4"}, {"caller_nid": "ledger_scene_summary_cliptext", "callee": "String", "source_file": "src\\main\\application\\script-generation\\ledger\\ledger-scene-summary.ts", "source_location": "L4"}, {"caller_nid": "ledger_scene_summary_cliptext", "callee": "trim", "source_file": "src\\main\\application\\script-generation\\ledger\\ledger-scene-summary.ts", "source_location": "L9"}, {"caller_nid": "ledger_scene_summary_cliptext", "callee": "slice", "source_file": "src\\main\\application\\script-generation\\ledger\\ledger-scene-summary.ts", "source_location": "L9"}, {"caller_nid": "ledger_scene_summary_cliptext", "callee": "max", "source_file": "src\\main\\application\\script-generation\\ledger\\ledger-scene-summary.ts", "source_location": "L9"}, {"caller_nid": "ledger_scene_summary_picksummarylines", "callee": "slice", "source_file": "src\\main\\application\\script-generation\\ledger\\ledger-scene-summary.ts", "source_location": "L13"}, {"caller_nid": "ledger_scene_summary_picksummarylines", "callee": "filter", "source_file": "src\\main\\application\\script-generation\\ledger\\ledger-scene-summary.ts", "source_location": "L13"}, {"caller_nid": "ledger_scene_summary_picksummarylines", "callee": "filter", "source_file": "src\\main\\application\\script-generation\\ledger\\ledger-scene-summary.ts", "source_location": "L13"}, {"caller_nid": "ledger_scene_summary_picksummarylines", "callee": "filter", "source_file": "src\\main\\application\\script-generation\\ledger\\ledger-scene-summary.ts", "source_location": "L13"}, {"caller_nid": "ledger_scene_summary_picksummarylines", "callee": "filter", "source_file": "src\\main\\application\\script-generation\\ledger\\ledger-scene-summary.ts", "source_location": "L13"}, {"caller_nid": "ledger_scene_summary_picksummarylines", "callee": "map", "source_file": "src\\main\\application\\script-generation\\ledger\\ledger-scene-summary.ts", "source_location": "L13"}, {"caller_nid": "ledger_scene_summary_picksummarylines", "callee": "split", "source_file": "src\\main\\application\\script-generation\\ledger\\ledger-scene-summary.ts", "source_location": "L13"}, {"caller_nid": "ledger_scene_summary_summarizescenefragment", "callee": "join", "source_file": "src\\main\\application\\script-generation\\ledger\\ledger-scene-summary.ts", "source_location": "L37"}, {"caller_nid": "ledger_scene_summary_summarizescenefragment", "callee": "filter", "source_file": "src\\main\\application\\script-generation\\ledger\\ledger-scene-summary.ts", "source_location": "L37"}, {"caller_nid": "ledger_scene_summary_summarizescenefragment", "callee": "map", "source_file": "src\\main\\application\\script-generation\\ledger\\ledger-scene-summary.ts", "source_location": "L37"}, {"caller_nid": "ledger_scene_summary_summarizescenefragment", "callee": "slice", "source_file": "src\\main\\application\\script-generation\\ledger\\ledger-scene-summary.ts", "source_location": "L37"}, {"caller_nid": "ledger_scene_summary_summarizescenefragment", "callee": "filter", "source_file": "src\\main\\application\\script-generation\\ledger\\ledger-scene-summary.ts", "source_location": "L44"}, {"caller_nid": "ledger_scene_summary_summarizescenefragment", "callee": "String", "source_file": "src\\main\\application\\script-generation\\ledger\\ledger-scene-summary.ts", "source_location": "L44"}, {"caller_nid": "ledger_scene_summary_summarizescenefragment", "callee": "join", "source_file": "src\\main\\application\\script-generation\\ledger\\ledger-scene-summary.ts", "source_location": "L47"}, {"caller_nid": "ledger_scene_summary_summarizescenefragment", "callee": "join", "source_file": "src\\main\\application\\script-generation\\ledger\\ledger-scene-summary.ts", "source_location": "L50"}, {"caller_nid": "ledger_scene_summary_summarizescenefragment", "callee": "join", "source_file": "src\\main\\application\\script-generation\\ledger\\ledger-scene-summary.ts", "source_location": "L53"}]}